<?xml version="1.0" ?>
 <ItemLookupResponse>
 <OperationRequest>
<HTTPHeaders>
<Header Name="UserAgent" Value="Ruby" />
</HTTPHeaders>
<RequestId>7bc3087a-8a6c-4da6-baed-184e726aba66</RequestId>
 <Arguments>
<Argument Name="AWSAccessKeyId" Value="AKIAIHMGKYWGXDTROKMA" />
<Argument Name="AssociateTag" Value="ventry-20" />
<Argument Name="ItemId" Value="B001JSX7KW,B00GMSTLN6,B00DC7DUHI,,B00BQ7B0MS,B00DI1H8B2,B00E3DXN04,B00A2UUJRW,B00N36C6BE,B00MMHUZWW" />
<Argument Name="Operation" Value="ItemLookup" />
<Argument Name="ResponseGroup" Value="Images,Offers,Small" />
<Argument Name="Service" Value="AWSECommerceService" />
<Argument Name="Timestamp" Value="2015-07-30T19:37:00Z" />
<Argument Name="Signature" Value="Xf3A5ix/Q7CJmcOWDW6JpFdpLX/pD78paUgzPYzO/cs=" />
 </Arguments>
<RequestProcessingTime>0.1379700000000000</RequestProcessingTime>
 </OperationRequest>
 <Items>
 <Request>
<IsValid>True</IsValid>
 <ItemLookupRequest>
<IdType>ASIN</IdType>
<ItemId>B001JSX7KW</ItemId>
<ItemId>B00GMSTLN6</ItemId>
<ItemId>B00DC7DUHI</ItemId>
<ItemId>B00BQ7B0MS</ItemId>
<ItemId>B00DI1H8B2</ItemId>
<ItemId>B00E3DXN04</ItemId>
<ItemId>B00A2UUJRW</ItemId>
<ItemId>B00N36C6BE</ItemId>
<ItemId>B00MMHUZWW</ItemId>
<ResponseGroup>Images</ResponseGroup>
<ResponseGroup>Offers</ResponseGroup>
<ResponseGroup>Small</ResponseGroup>
<VariationPage>All</VariationPage>
 </ItemLookupRequest>
 </Request>
 <Item>
<ASIN>B001JSX7KW</ASIN>
<DetailPageURL>http://www.amazon.com/Shot-Glass-Roulette-Drinking-Glasses/dp/B001JSX7KW%3FSubscriptionId%3DAKIAIHMGKYWGXDTROKMA%26tag%3Dventry-20%26linkCode%3Dxm2%26camp%3D2025%26creative%3D165953%26creativeASIN%3DB001JSX7KW</DetailPageURL>
 <ItemLinks>
 <ItemLink>
<Description>Technical Details</Description>
<URL>http://www.amazon.com/Shot-Glass-Roulette-Drinking-Glasses/dp/tech-data/B001JSX7KW%3FSubscriptionId%3DAKIAIHMGKYWGXDTROKMA%26tag%3Dventry-20%26linkCode%3Dxm2%26camp%3D2025%26creative%3D386001%26creativeASIN%3DB001JSX7KW</URL>
 </ItemLink>
 <ItemLink>
<Description>Add To Baby Registry</Description>
<URL>http://www.amazon.com/gp/registry/baby/add-item.html%3Fasin.0%3DB001JSX7KW%26SubscriptionId%3DAKIAIHMGKYWGXDTROKMA%26tag%3Dventry-20%26linkCode%3Dxm2%26camp%3D2025%26creative%3D386001%26creativeASIN%3DB001JSX7KW</URL>
 </ItemLink>
 <ItemLink>
<Description>Add To Wedding Registry</Description>
<URL>http://www.amazon.com/gp/registry/wedding/add-item.html%3Fasin.0%3DB001JSX7KW%26SubscriptionId%3DAKIAIHMGKYWGXDTROKMA%26tag%3Dventry-20%26linkCode%3Dxm2%26camp%3D2025%26creative%3D386001%26creativeASIN%3DB001JSX7KW</URL>
 </ItemLink>
 <ItemLink>
<Description>Add To Wishlist</Description>
<URL>http://www.amazon.com/gp/registry/wishlist/add-item.html%3Fasin.0%3DB001JSX7KW%26SubscriptionId%3DAKIAIHMGKYWGXDTROKMA%26tag%3Dventry-20%26linkCode%3Dxm2%26camp%3D2025%26creative%3D386001%26creativeASIN%3DB001JSX7KW</URL>
 </ItemLink>
 <ItemLink>
<Description>Tell A Friend</Description>
<URL>http://www.amazon.com/gp/pdp/taf/B001JSX7KW%3FSubscriptionId%3DAKIAIHMGKYWGXDTROKMA%26tag%3Dventry-20%26linkCode%3Dxm2%26camp%3D2025%26creative%3D386001%26creativeASIN%3DB001JSX7KW</URL>
 </ItemLink>
 <ItemLink>
<Description>All Customer Reviews</Description>
<URL>http://www.amazon.com/review/product/B001JSX7KW%3FSubscriptionId%3DAKIAIHMGKYWGXDTROKMA%26tag%3Dventry-20%26linkCode%3Dxm2%26camp%3D2025%26creative%3D386001%26creativeASIN%3DB001JSX7KW</URL>
 </ItemLink>
 <ItemLink>
<Description>All Offers</Description>
<URL>http://www.amazon.com/gp/offer-listing/B001JSX7KW%3FSubscriptionId%3DAKIAIHMGKYWGXDTROKMA%26tag%3Dventry-20%26linkCode%3Dxm2%26camp%3D2025%26creative%3D386001%26creativeASIN%3DB001JSX7KW</URL>
 </ItemLink>
 </ItemLinks>
 <SmallImage>
<URL>http://ecx.images-amazon.com/images/I/51L6MC4lgbL._SL75_.jpg</URL>
<Height Units="pixels">66</Height>
<Width Units="pixels">75</Width>
 </SmallImage>
 <MediumImage>
<URL>http://ecx.images-amazon.com/images/I/51L6MC4lgbL._SL160_.jpg</URL>
<Height Units="pixels">142</Height>
<Width Units="pixels">160</Width>
 </MediumImage>
 <LargeImage>
<URL>http://ecx.images-amazon.com/images/I/51L6MC4lgbL.jpg</URL>
<Height Units="pixels">443</Height>
<Width Units="pixels">500</Width>
 </LargeImage>
<ImageSets>
 <ImageSet Category="primary">
 <SwatchImage>
<URL>http://ecx.images-amazon.com/images/I/51L6MC4lgbL._SL30_.jpg</URL>
<Height Units="pixels">27</Height>
<Width Units="pixels">30</Width>
 </SwatchImage>
 <SmallImage>
<URL>http://ecx.images-amazon.com/images/I/51L6MC4lgbL._SL75_.jpg</URL>
<Height Units="pixels">66</Height>
<Width Units="pixels">75</Width>
 </SmallImage>
 <ThumbnailImage>
<URL>http://ecx.images-amazon.com/images/I/51L6MC4lgbL._SL75_.jpg</URL>
<Height Units="pixels">66</Height>
<Width Units="pixels">75</Width>
 </ThumbnailImage>
 <TinyImage>
<URL>http://ecx.images-amazon.com/images/I/51L6MC4lgbL._SL110_.jpg</URL>
<Height Units="pixels">97</Height>
<Width Units="pixels">110</Width>
 </TinyImage>
 <MediumImage>
<URL>http://ecx.images-amazon.com/images/I/51L6MC4lgbL._SL160_.jpg</URL>
<Height Units="pixels">142</Height>
<Width Units="pixels">160</Width>
 </MediumImage>
 <LargeImage>
<URL>http://ecx.images-amazon.com/images/I/51L6MC4lgbL.jpg</URL>
<Height Units="pixels">443</Height>
<Width Units="pixels">500</Width>
 </LargeImage>
 </ImageSet>
</ImageSets>
 <ItemAttributes>
<Manufacturer>Fairly Odd Treasures LLC - Kitchen</Manufacturer>
<ProductGroup>Kitchen</ProductGroup>
<Title>Shot Glass Roulette - Drinking Game Set (2 Balls and 16 Glasses)</Title>
 </ItemAttributes>
 <OfferSummary>
 <LowestNewPrice>
<Amount>1049</Amount>
<CurrencyCode>USD</CurrencyCode>
<FormattedPrice>$10.49</FormattedPrice>
 </LowestNewPrice>
 <LowestUsedPrice>
<Amount>1443</Amount>
<CurrencyCode>USD</CurrencyCode>
<FormattedPrice>$14.43</FormattedPrice>
 </LowestUsedPrice>
<TotalNew>27</TotalNew>
<TotalUsed>6</TotalUsed>
<TotalCollectible>0</TotalCollectible>
<TotalRefurbished>0</TotalRefurbished>
 </OfferSummary>
 <Offers>
<TotalOffers>1</TotalOffers>
<TotalOfferPages>1</TotalOfferPages>
<MoreOffersUrl>http://www.amazon.com/gp/offer-listing/B001JSX7KW%3FSubscriptionId%3DAKIAIHMGKYWGXDTROKMA%26tag%3Dventry-20%26linkCode%3Dxm2%26camp%3D2025%26creative%3D386001%26creativeASIN%3DB001JSX7KW</MoreOffersUrl>
 <Offer>
<OfferAttributes>
<Condition>New</Condition>
</OfferAttributes>
 <OfferListing>
<OfferListingId>CCoTtR%2FrqwAUp3cMgBZ3tQpclxddWtqKcj0BO9oUzvZYikhX8zhhlCx1BsPWg7UkriLyf1mxG%2F6LrzH3313vmkIEa%2Fhjfd4Yvym95gQDFeVyLt%2Fbb21RXhhm9Pcg9UYMeeD5rrttLhHMmP0CDswigwkdGvBZ2%2BAc</OfferListingId>
 <Price>
<Amount>1198</Amount>
<CurrencyCode>USD</CurrencyCode>
<FormattedPrice>$11.98</FormattedPrice>
 </Price>
 <AmountSaved>
<Amount>3801</Amount>
<CurrencyCode>USD</CurrencyCode>
<FormattedPrice>$38.01</FormattedPrice>
 </AmountSaved>
<PercentageSaved>76</PercentageSaved>
<Availability>Usually ships in 24 hours</Availability>
 <AvailabilityAttributes>
<AvailabilityType>now</AvailabilityType>
<MinimumHours>0</MinimumHours>
<MaximumHours>0</MaximumHours>
 </AvailabilityAttributes>
<IsEligibleForSuperSaverShipping>0</IsEligibleForSuperSaverShipping>
 </OfferListing>
 </Offer>
 </Offers>
 </Item>
 <Item>
<ASIN>B00GMSTLN6</ASIN>
<ParentASIN>B00PZ3KMWS</ParentASIN>
<DetailPageURL>http://www.amazon.com/Light-Up-Wire-Glasses-Orange/dp/B00GMSTLN6%3Fpsc%3D1%26SubscriptionId%3DAKIAIHMGKYWGXDTROKMA%26tag%3Dventry-20%26linkCode%3Dxm2%26camp%3D2025%26creative%3D165953%26creativeASIN%3DB00GMSTLN6</DetailPageURL>
 <ItemLinks>
 <ItemLink>
<Description>Technical Details</Description>
<URL>http://www.amazon.com/Light-Up-Wire-Glasses-Orange/dp/tech-data/B00GMSTLN6%3FSubscriptionId%3DAKIAIHMGKYWGXDTROKMA%26tag%3Dventry-20%26linkCode%3Dxm2%26camp%3D2025%26creative%3D386001%26creativeASIN%3DB00GMSTLN6</URL>
 </ItemLink>
 <ItemLink>
<Description>Add To Baby Registry</Description>
<URL>http://www.amazon.com/gp/registry/baby/add-item.html%3Fasin.0%3DB00GMSTLN6%26SubscriptionId%3DAKIAIHMGKYWGXDTROKMA%26tag%3Dventry-20%26linkCode%3Dxm2%26camp%3D2025%26creative%3D386001%26creativeASIN%3DB00GMSTLN6</URL>
 </ItemLink>
 <ItemLink>
<Description>Add To Wedding Registry</Description>
<URL>http://www.amazon.com/gp/registry/wedding/add-item.html%3Fasin.0%3DB00GMSTLN6%26SubscriptionId%3DAKIAIHMGKYWGXDTROKMA%26tag%3Dventry-20%26linkCode%3Dxm2%26camp%3D2025%26creative%3D386001%26creativeASIN%3DB00GMSTLN6</URL>
 </ItemLink>
 <ItemLink>
<Description>Add To Wishlist</Description>
<URL>http://www.amazon.com/gp/registry/wishlist/add-item.html%3Fasin.0%3DB00GMSTLN6%26SubscriptionId%3DAKIAIHMGKYWGXDTROKMA%26tag%3Dventry-20%26linkCode%3Dxm2%26camp%3D2025%26creative%3D386001%26creativeASIN%3DB00GMSTLN6</URL>
 </ItemLink>
 <ItemLink>
<Description>Tell A Friend</Description>
<URL>http://www.amazon.com/gp/pdp/taf/B00GMSTLN6%3FSubscriptionId%3DAKIAIHMGKYWGXDTROKMA%26tag%3Dventry-20%26linkCode%3Dxm2%26camp%3D2025%26creative%3D386001%26creativeASIN%3DB00GMSTLN6</URL>
 </ItemLink>
 <ItemLink>
<Description>All Customer Reviews</Description>
<URL>http://www.amazon.com/review/product/B00GMSTLN6%3FSubscriptionId%3DAKIAIHMGKYWGXDTROKMA%26tag%3Dventry-20%26linkCode%3Dxm2%26camp%3D2025%26creative%3D386001%26creativeASIN%3DB00GMSTLN6</URL>
 </ItemLink>
 <ItemLink>
<Description>All Offers</Description>
<URL>http://www.amazon.com/gp/offer-listing/B00GMSTLN6%3FSubscriptionId%3DAKIAIHMGKYWGXDTROKMA%26tag%3Dventry-20%26linkCode%3Dxm2%26camp%3D2025%26creative%3D386001%26creativeASIN%3DB00GMSTLN6</URL>
 </ItemLink>
 </ItemLinks>
 <SmallImage>
<URL>http://ecx.images-amazon.com/images/I/41lZ9XwplJL._SL75_.jpg</URL>
<Height Units="pixels">75</Height>
<Width Units="pixels">60</Width>
 </SmallImage>
 <MediumImage>
<URL>http://ecx.images-amazon.com/images/I/41lZ9XwplJL._SL160_.jpg</URL>
<Height Units="pixels">160</Height>
<Width Units="pixels">128</Width>
 </MediumImage>
 <LargeImage>
<URL>http://ecx.images-amazon.com/images/I/41lZ9XwplJL.jpg</URL>
<Height Units="pixels">500</Height>
<Width Units="pixels">400</Width>
 </LargeImage>
 <ImageSets>
 <ImageSet Category="variant">
 <SwatchImage>
<URL>http://ecx.images-amazon.com/images/I/41FPZk5ytUL._SL30_.jpg</URL>
<Height Units="pixels">30</Height>
<Width Units="pixels">24</Width>
 </SwatchImage>
 <SmallImage>
<URL>http://ecx.images-amazon.com/images/I/41FPZk5ytUL._SL75_.jpg</URL>
<Height Units="pixels">75</Height>
<Width Units="pixels">60</Width>
 </SmallImage>
 <ThumbnailImage>
<URL>http://ecx.images-amazon.com/images/I/41FPZk5ytUL._SL75_.jpg</URL>
<Height Units="pixels">75</Height>
<Width Units="pixels">60</Width>
 </ThumbnailImage>
 <TinyImage>
<URL>http://ecx.images-amazon.com/images/I/41FPZk5ytUL._SL110_.jpg</URL>
<Height Units="pixels">110</Height>
<Width Units="pixels">88</Width>
 </TinyImage>
 <MediumImage>
<URL>http://ecx.images-amazon.com/images/I/41FPZk5ytUL._SL160_.jpg</URL>
<Height Units="pixels">160</Height>
<Width Units="pixels">128</Width>
 </MediumImage>
 <LargeImage>
<URL>http://ecx.images-amazon.com/images/I/41FPZk5ytUL.jpg</URL>
<Height Units="pixels">500</Height>
<Width Units="pixels">400</Width>
 </LargeImage>
 </ImageSet>
 <ImageSet Category="variant">
 <SwatchImage>
<URL>http://ecx.images-amazon.com/images/I/413x3Gl0CTL._SL30_.jpg</URL>
<Height Units="pixels">30</Height>
<Width Units="pixels">24</Width>
 </SwatchImage>
 <SmallImage>
<URL>http://ecx.images-amazon.com/images/I/413x3Gl0CTL._SL75_.jpg</URL>
<Height Units="pixels">75</Height>
<Width Units="pixels">60</Width>
 </SmallImage>
 <ThumbnailImage>
<URL>http://ecx.images-amazon.com/images/I/413x3Gl0CTL._SL75_.jpg</URL>
<Height Units="pixels">75</Height>
<Width Units="pixels">60</Width>
 </ThumbnailImage>
 <TinyImage>
<URL>http://ecx.images-amazon.com/images/I/413x3Gl0CTL._SL110_.jpg</URL>
<Height Units="pixels">110</Height>
<Width Units="pixels">88</Width>
 </TinyImage>
 <MediumImage>
<URL>http://ecx.images-amazon.com/images/I/413x3Gl0CTL._SL160_.jpg</URL>
<Height Units="pixels">160</Height>
<Width Units="pixels">128</Width>
 </MediumImage>
 <LargeImage>
<URL>http://ecx.images-amazon.com/images/I/413x3Gl0CTL.jpg</URL>
<Height Units="pixels">500</Height>
<Width Units="pixels">400</Width>
 </LargeImage>
 </ImageSet>
 <ImageSet Category="primary">
 <SwatchImage>
<URL>http://ecx.images-amazon.com/images/I/41lZ9XwplJL._SL30_.jpg</URL>
<Height Units="pixels">30</Height>
<Width Units="pixels">24</Width>
 </SwatchImage>
 <SmallImage>
<URL>http://ecx.images-amazon.com/images/I/41lZ9XwplJL._SL75_.jpg</URL>
<Height Units="pixels">75</Height>
<Width Units="pixels">60</Width>
 </SmallImage>
 <ThumbnailImage>
<URL>http://ecx.images-amazon.com/images/I/41lZ9XwplJL._SL75_.jpg</URL>
<Height Units="pixels">75</Height>
<Width Units="pixels">60</Width>
 </ThumbnailImage>
 <TinyImage>
<URL>http://ecx.images-amazon.com/images/I/41lZ9XwplJL._SL110_.jpg</URL>
<Height Units="pixels">110</Height>
<Width Units="pixels">88</Width>
 </TinyImage>
 <MediumImage>
<URL>http://ecx.images-amazon.com/images/I/41lZ9XwplJL._SL160_.jpg</URL>
<Height Units="pixels">160</Height>
<Width Units="pixels">128</Width>
 </MediumImage>
 <LargeImage>
<URL>http://ecx.images-amazon.com/images/I/41lZ9XwplJL.jpg</URL>
<Height Units="pixels">500</Height>
<Width Units="pixels">400</Width>
 </LargeImage>
 </ImageSet>
 </ImageSets>
 <ItemAttributes>
<ProductGroup>Apparel</ProductGroup>
<Title>Light Up El Wire Glasses (Orange)</Title>
 </ItemAttributes>
 <OfferSummary>
 <LowestNewPrice>
<Amount>1997</Amount>
<CurrencyCode>USD</CurrencyCode>
<FormattedPrice>$19.97</FormattedPrice>
 </LowestNewPrice>
<TotalNew>1</TotalNew>
<TotalUsed>0</TotalUsed>
<TotalCollectible>0</TotalCollectible>
<TotalRefurbished>0</TotalRefurbished>
 </OfferSummary>
 <Offers>
<TotalOffers>1</TotalOffers>
<TotalOfferPages>1</TotalOfferPages>
<MoreOffersUrl>http://www.amazon.com/gp/offer-listing/B00GMSTLN6%3FSubscriptionId%3DAKIAIHMGKYWGXDTROKMA%26tag%3Dventry-20%26linkCode%3Dxm2%26camp%3D2025%26creative%3D386001%26creativeASIN%3DB00GMSTLN6</MoreOffersUrl>
 <Offer>
<OfferAttributes>
<Condition>New</Condition>
</OfferAttributes>
 <OfferListing>
<OfferListingId>NERbE2DriDKiMv9FOA9s0KWlVoxuv%2FINS7JR3NAox6FJ681NvNDsRK3xI2xrZl%2FcTq8y3GtQF9PKY6ZPzb54PlKd%2Fxmoeh5vN4qH1B1ODQxO5kvQ3h3hT57fhiaLH6uDp1aPXduYC2i9QtmLNDSSB%2BDS9Sx37pku</OfferListingId>
 <Price>
<Amount>2497</Amount>
<CurrencyCode>USD</CurrencyCode>
<FormattedPrice>$24.97</FormattedPrice>
 </Price>
 <SalePrice>
<Amount>1997</Amount>
<CurrencyCode>USD</CurrencyCode>
<FormattedPrice>$19.97</FormattedPrice>
 </SalePrice>
 <AmountSaved>
<Amount>500</Amount>
<CurrencyCode>USD</CurrencyCode>
<FormattedPrice>$5.00</FormattedPrice>
 </AmountSaved>
<PercentageSaved>20</PercentageSaved>
<Availability>Usually ships in 24 hours</Availability>
 <AvailabilityAttributes>
<AvailabilityType>now</AvailabilityType>
<MinimumHours>0</MinimumHours>
<MaximumHours>0</MaximumHours>
 </AvailabilityAttributes>
<IsEligibleForSuperSaverShipping>1</IsEligibleForSuperSaverShipping>
 </OfferListing>
 </Offer>
 </Offers>
 </Item>
 <Item>
<ASIN>B00DC7DUHI</ASIN>
<ParentASIN>B00DC7DUHI</ParentASIN>
<DetailPageURL>http://www.amazon.com/About-Llama-Shirt-Funny-Llamas/dp/B00DC7DUHI%3FSubscriptionId%3DAKIAIHMGKYWGXDTROKMA%26tag%3Dventry-20%26linkCode%3Dxm2%26camp%3D2025%26creative%3D165953%26creativeASIN%3DB00DC7DUHI</DetailPageURL>
 <ItemLinks>
 <ItemLink>
<Description>Technical Details</Description>
<URL>http://www.amazon.com/About-Llama-Shirt-Funny-Llamas/dp/tech-data/B00DC7DUHI%3FSubscriptionId%3DAKIAIHMGKYWGXDTROKMA%26tag%3Dventry-20%26linkCode%3Dxm2%26camp%3D2025%26creative%3D386001%26creativeASIN%3DB00DC7DUHI</URL>
 </ItemLink>
 <ItemLink>
<Description>Add To Baby Registry</Description>
<URL>http://www.amazon.com/gp/registry/baby/add-item.html%3Fasin.0%3DB00DC7DUHI%26SubscriptionId%3DAKIAIHMGKYWGXDTROKMA%26tag%3Dventry-20%26linkCode%3Dxm2%26camp%3D2025%26creative%3D386001%26creativeASIN%3DB00DC7DUHI</URL>
 </ItemLink>
 <ItemLink>
<Description>Add To Wedding Registry</Description>
<URL>http://www.amazon.com/gp/registry/wedding/add-item.html%3Fasin.0%3DB00DC7DUHI%26SubscriptionId%3DAKIAIHMGKYWGXDTROKMA%26tag%3Dventry-20%26linkCode%3Dxm2%26camp%3D2025%26creative%3D386001%26creativeASIN%3DB00DC7DUHI</URL>
 </ItemLink>
 <ItemLink>
<Description>Add To Wishlist</Description>
<URL>http://www.amazon.com/gp/registry/wishlist/add-item.html%3Fasin.0%3DB00DC7DUHI%26SubscriptionId%3DAKIAIHMGKYWGXDTROKMA%26tag%3Dventry-20%26linkCode%3Dxm2%26camp%3D2025%26creative%3D386001%26creativeASIN%3DB00DC7DUHI</URL>
 </ItemLink>
 <ItemLink>
<Description>Tell A Friend</Description>
<URL>http://www.amazon.com/gp/pdp/taf/B00DC7DUHI%3FSubscriptionId%3DAKIAIHMGKYWGXDTROKMA%26tag%3Dventry-20%26linkCode%3Dxm2%26camp%3D2025%26creative%3D386001%26creativeASIN%3DB00DC7DUHI</URL>
 </ItemLink>
 <ItemLink>
<Description>All Customer Reviews</Description>
<URL>http://www.amazon.com/review/product/B00DC7DUHI%3FSubscriptionId%3DAKIAIHMGKYWGXDTROKMA%26tag%3Dventry-20%26linkCode%3Dxm2%26camp%3D2025%26creative%3D386001%26creativeASIN%3DB00DC7DUHI</URL>
 </ItemLink>
 <ItemLink>
<Description>All Offers</Description>
<URL>http://www.amazon.com/gp/offer-listing/B00DC7DUHI%3FSubscriptionId%3DAKIAIHMGKYWGXDTROKMA%26tag%3Dventry-20%26linkCode%3Dxm2%26camp%3D2025%26creative%3D386001%26creativeASIN%3DB00DC7DUHI</URL>
 </ItemLink>
 </ItemLinks>
 <SmallImage>
<URL>http://ecx.images-amazon.com/images/I/411mUqCMgHL._SL75_.jpg</URL>
<Height Units="pixels">75</Height>
<Width Units="pixels">49</Width>
 </SmallImage>
 <MediumImage>
<URL>http://ecx.images-amazon.com/images/I/411mUqCMgHL._SL160_.jpg</URL>
<Height Units="pixels">160</Height>
<Width Units="pixels">105</Width>
 </MediumImage>
 <LargeImage>
<URL>http://ecx.images-amazon.com/images/I/411mUqCMgHL.jpg</URL>
<Height Units="pixels">500</Height>
<Width Units="pixels">329</Width>
 </LargeImage>
 <ImageSets>
 <ImageSet Category="variant">
 <SwatchImage>
<URL>http://ecx.images-amazon.com/images/I/51JWTG%2BaVOL._SL30_.jpg</URL>
<Height Units="pixels">30</Height>
<Width Units="pixels">25</Width>
 </SwatchImage>
 <SmallImage>
<URL>http://ecx.images-amazon.com/images/I/51JWTG%2BaVOL._SL75_.jpg</URL>
<Height Units="pixels">75</Height>
<Width Units="pixels">61</Width>
 </SmallImage>
 <ThumbnailImage>
<URL>http://ecx.images-amazon.com/images/I/51JWTG%2BaVOL._SL75_.jpg</URL>
<Height Units="pixels">75</Height>
<Width Units="pixels">61</Width>
 </ThumbnailImage>
 <TinyImage>
<URL>http://ecx.images-amazon.com/images/I/51JWTG%2BaVOL._SL110_.jpg</URL>
<Height Units="pixels">110</Height>
<Width Units="pixels">90</Width>
 </TinyImage>
 <MediumImage>
<URL>http://ecx.images-amazon.com/images/I/51JWTG%2BaVOL._SL160_.jpg</URL>
<Height Units="pixels">160</Height>
<Width Units="pixels">131</Width>
 </MediumImage>
 <LargeImage>
<URL>http://ecx.images-amazon.com/images/I/51JWTG%2BaVOL.jpg</URL>
<Height Units="pixels">500</Height>
<Width Units="pixels">409</Width>
 </LargeImage>
 </ImageSet>
 <ImageSet Category="primary">
 <SwatchImage>
<URL>http://ecx.images-amazon.com/images/I/411mUqCMgHL._SL30_.jpg</URL>
<Height Units="pixels">30</Height>
<Width Units="pixels">20</Width>
 </SwatchImage>
 <SmallImage>
<URL>http://ecx.images-amazon.com/images/I/411mUqCMgHL._SL75_.jpg</URL>
<Height Units="pixels">75</Height>
<Width Units="pixels">49</Width>
 </SmallImage>
 <ThumbnailImage>
<URL>http://ecx.images-amazon.com/images/I/411mUqCMgHL._SL75_.jpg</URL>
<Height Units="pixels">75</Height>
<Width Units="pixels">49</Width>
 </ThumbnailImage>
 <TinyImage>
<URL>http://ecx.images-amazon.com/images/I/411mUqCMgHL._SL110_.jpg</URL>
<Height Units="pixels">110</Height>
<Width Units="pixels">72</Width>
 </TinyImage>
 <MediumImage>
<URL>http://ecx.images-amazon.com/images/I/411mUqCMgHL._SL160_.jpg</URL>
<Height Units="pixels">160</Height>
<Width Units="pixels">105</Width>
 </MediumImage>
 <LargeImage>
<URL>http://ecx.images-amazon.com/images/I/411mUqCMgHL.jpg</URL>
<Height Units="pixels">500</Height>
<Width Units="pixels">329</Width>
 </LargeImage>
 </ImageSet>
 </ImageSets>
 <ItemAttributes>
<Manufacturer>Crazy Dog</Manufacturer>
<ProductGroup>Apparel</ProductGroup>
<Title>Ask Me About My Llama T Shirt Funny Llama Flip Shirt Llamas Tee</Title>
 </ItemAttributes>
 <OfferSummary>
<TotalNew>0</TotalNew>
<TotalUsed>0</TotalUsed>
<TotalCollectible>0</TotalCollectible>
<TotalRefurbished>0</TotalRefurbished>
 </OfferSummary>
 <Offers>
<TotalOffers>0</TotalOffers>
<TotalOfferPages>0</TotalOfferPages>
<MoreOffersUrl>0</MoreOffersUrl>
 </Offers>
 </Item>
 <Item>
<ASIN>B00BQ7B0MS</ASIN>
<DetailPageURL>http://www.amazon.com/Champion-Sports-Anywhere-Table-Tennis/dp/B00BQ7B0MS%3FSubscriptionId%3DAKIAIHMGKYWGXDTROKMA%26tag%3Dventry-20%26linkCode%3Dxm2%26camp%3D2025%26creative%3D165953%26creativeASIN%3DB00BQ7B0MS</DetailPageURL>
 <ItemLinks>
 <ItemLink>
<Description>Technical Details</Description>
<URL>http://www.amazon.com/Champion-Sports-Anywhere-Table-Tennis/dp/tech-data/B00BQ7B0MS%3FSubscriptionId%3DAKIAIHMGKYWGXDTROKMA%26tag%3Dventry-20%26linkCode%3Dxm2%26camp%3D2025%26creative%3D386001%26creativeASIN%3DB00BQ7B0MS</URL>
 </ItemLink>
 <ItemLink>
<Description>Add To Baby Registry</Description>
<URL>http://www.amazon.com/gp/registry/baby/add-item.html%3Fasin.0%3DB00BQ7B0MS%26SubscriptionId%3DAKIAIHMGKYWGXDTROKMA%26tag%3Dventry-20%26linkCode%3Dxm2%26camp%3D2025%26creative%3D386001%26creativeASIN%3DB00BQ7B0MS</URL>
 </ItemLink>
 <ItemLink>
<Description>Add To Wedding Registry</Description>
<URL>http://www.amazon.com/gp/registry/wedding/add-item.html%3Fasin.0%3DB00BQ7B0MS%26SubscriptionId%3DAKIAIHMGKYWGXDTROKMA%26tag%3Dventry-20%26linkCode%3Dxm2%26camp%3D2025%26creative%3D386001%26creativeASIN%3DB00BQ7B0MS</URL>
 </ItemLink>
 <ItemLink>
<Description>Add To Wishlist</Description>
<URL>http://www.amazon.com/gp/registry/wishlist/add-item.html%3Fasin.0%3DB00BQ7B0MS%26SubscriptionId%3DAKIAIHMGKYWGXDTROKMA%26tag%3Dventry-20%26linkCode%3Dxm2%26camp%3D2025%26creative%3D386001%26creativeASIN%3DB00BQ7B0MS</URL>
 </ItemLink>
 <ItemLink>
<Description>Tell A Friend</Description>
<URL>http://www.amazon.com/gp/pdp/taf/B00BQ7B0MS%3FSubscriptionId%3DAKIAIHMGKYWGXDTROKMA%26tag%3Dventry-20%26linkCode%3Dxm2%26camp%3D2025%26creative%3D386001%26creativeASIN%3DB00BQ7B0MS</URL>
 </ItemLink>
 <ItemLink>
<Description>All Customer Reviews</Description>
<URL>http://www.amazon.com/review/product/B00BQ7B0MS%3FSubscriptionId%3DAKIAIHMGKYWGXDTROKMA%26tag%3Dventry-20%26linkCode%3Dxm2%26camp%3D2025%26creative%3D386001%26creativeASIN%3DB00BQ7B0MS</URL>
 </ItemLink>
 <ItemLink>
<Description>All Offers</Description>
<URL>http://www.amazon.com/gp/offer-listing/B00BQ7B0MS%3FSubscriptionId%3DAKIAIHMGKYWGXDTROKMA%26tag%3Dventry-20%26linkCode%3Dxm2%26camp%3D2025%26creative%3D386001%26creativeASIN%3DB00BQ7B0MS</URL>
 </ItemLink>
 </ItemLinks>
 <SmallImage>
<URL>http://ecx.images-amazon.com/images/I/51Afw0Dkj3L._SL75_.jpg</URL>
<Height Units="pixels">66</Height>
<Width Units="pixels">75</Width>
 </SmallImage>
 <MediumImage>
<URL>http://ecx.images-amazon.com/images/I/51Afw0Dkj3L._SL160_.jpg</URL>
<Height Units="pixels">141</Height>
<Width Units="pixels">160</Width>
 </MediumImage>
 <LargeImage>
<URL>http://ecx.images-amazon.com/images/I/51Afw0Dkj3L.jpg</URL>
<Height Units="pixels">440</Height>
<Width Units="pixels">500</Width>
 </LargeImage>
 <ImageSets>
 <ImageSet Category="swatch">
 <SwatchImage>
<URL>http://ecx.images-amazon.com/images/I/51Afw0Dkj3L._SL30_.jpg</URL>
<Height Units="pixels">26</Height>
<Width Units="pixels">30</Width>
 </SwatchImage>
 <SmallImage>
<URL>http://ecx.images-amazon.com/images/I/51Afw0Dkj3L._SL75_.jpg</URL>
<Height Units="pixels">66</Height>
<Width Units="pixels">75</Width>
 </SmallImage>
 <ThumbnailImage>
<URL>http://ecx.images-amazon.com/images/I/51Afw0Dkj3L._SL75_.jpg</URL>
<Height Units="pixels">66</Height>
<Width Units="pixels">75</Width>
 </ThumbnailImage>
 <TinyImage>
<URL>http://ecx.images-amazon.com/images/I/51Afw0Dkj3L._SL110_.jpg</URL>
<Height Units="pixels">97</Height>
<Width Units="pixels">110</Width>
 </TinyImage>
 <MediumImage>
<URL>http://ecx.images-amazon.com/images/I/51Afw0Dkj3L._SL160_.jpg</URL>
<Height Units="pixels">141</Height>
<Width Units="pixels">160</Width>
 </MediumImage>
 <LargeImage>
<URL>http://ecx.images-amazon.com/images/I/51Afw0Dkj3L.jpg</URL>
<Height Units="pixels">440</Height>
<Width Units="pixels">500</Width>
 </LargeImage>
 </ImageSet>
 <ImageSet Category="variant">
 <SwatchImage>
<URL>http://ecx.images-amazon.com/images/I/416TbwU9N4L._SL30_.jpg</URL>
<Height Units="pixels">20</Height>
<Width Units="pixels">30</Width>
 </SwatchImage>
 <SmallImage>
<URL>http://ecx.images-amazon.com/images/I/416TbwU9N4L._SL75_.jpg</URL>
<Height Units="pixels">50</Height>
<Width Units="pixels">75</Width>
 </SmallImage>
 <ThumbnailImage>
<URL>http://ecx.images-amazon.com/images/I/416TbwU9N4L._SL75_.jpg</URL>
<Height Units="pixels">50</Height>
<Width Units="pixels">75</Width>
 </ThumbnailImage>
 <TinyImage>
<URL>http://ecx.images-amazon.com/images/I/416TbwU9N4L._SL110_.jpg</URL>
<Height Units="pixels">73</Height>
<Width Units="pixels">110</Width>
 </TinyImage>
 <MediumImage>
<URL>http://ecx.images-amazon.com/images/I/416TbwU9N4L._SL160_.jpg</URL>
<Height Units="pixels">107</Height>
<Width Units="pixels">160</Width>
 </MediumImage>
 <LargeImage>
<URL>http://ecx.images-amazon.com/images/I/416TbwU9N4L.jpg</URL>
<Height Units="pixels">333</Height>
<Width Units="pixels">500</Width>
 </LargeImage>
 </ImageSet>
 <ImageSet Category="primary">
 <SwatchImage>
<URL>http://ecx.images-amazon.com/images/I/51Afw0Dkj3L._SL30_.jpg</URL>
<Height Units="pixels">26</Height>
<Width Units="pixels">30</Width>
 </SwatchImage>
 <SmallImage>
<URL>http://ecx.images-amazon.com/images/I/51Afw0Dkj3L._SL75_.jpg</URL>
<Height Units="pixels">66</Height>
<Width Units="pixels">75</Width>
 </SmallImage>
 <ThumbnailImage>
<URL>http://ecx.images-amazon.com/images/I/51Afw0Dkj3L._SL75_.jpg</URL>
<Height Units="pixels">66</Height>
<Width Units="pixels">75</Width>
 </ThumbnailImage>
 <TinyImage>
<URL>http://ecx.images-amazon.com/images/I/51Afw0Dkj3L._SL110_.jpg</URL>
<Height Units="pixels">97</Height>
<Width Units="pixels">110</Width>
 </TinyImage>
 <MediumImage>
<URL>http://ecx.images-amazon.com/images/I/51Afw0Dkj3L._SL160_.jpg</URL>
<Height Units="pixels">141</Height>
<Width Units="pixels">160</Width>
 </MediumImage>
 <LargeImage>
<URL>http://ecx.images-amazon.com/images/I/51Afw0Dkj3L.jpg</URL>
<Height Units="pixels">440</Height>
<Width Units="pixels">500</Width>
 </LargeImage>
 </ImageSet>
 </ImageSets>
 <ItemAttributes>
<Manufacturer>Champion Sports</Manufacturer>
<ProductGroup>Sports</ProductGroup>
<Title>Champion Sports Anywhere Table Tennis To Go Set</Title>
 </ItemAttributes>
 <OfferSummary>
 <LowestNewPrice>
<Amount>1999</Amount>
<CurrencyCode>USD</CurrencyCode>
<FormattedPrice>$19.99</FormattedPrice>
 </LowestNewPrice>
 <LowestUsedPrice>
<Amount>1626</Amount>
<CurrencyCode>USD</CurrencyCode>
<FormattedPrice>$16.26</FormattedPrice>
 </LowestUsedPrice>
<TotalNew>8</TotalNew>
<TotalUsed>2</TotalUsed>
<TotalCollectible>0</TotalCollectible>
<TotalRefurbished>0</TotalRefurbished>
 </OfferSummary>
 <Offers>
<TotalOffers>1</TotalOffers>
<TotalOfferPages>1</TotalOfferPages>
<MoreOffersUrl>http://www.amazon.com/gp/offer-listing/B00BQ7B0MS%3FSubscriptionId%3DAKIAIHMGKYWGXDTROKMA%26tag%3Dventry-20%26linkCode%3Dxm2%26camp%3D2025%26creative%3D386001%26creativeASIN%3DB00BQ7B0MS</MoreOffersUrl>
 <Offer>
<OfferAttributes>
<Condition>New</Condition>
</OfferAttributes>
 <OfferListing>
<OfferListingId>Ihwl3YYvC73sondcq1QAQB8CdrpUfOFxgXMLDQG28J%2B96B0ra4Rof6dOp%2FBEUGNQbS%2B2i9ZsQBEfki7oZ7yr9kBEQ3v8WZSGjdHewNT85urS2AqO8GgNKQ%3D%3D</OfferListingId>
 <Price>
<Amount>2090</Amount>
<CurrencyCode>USD</CurrencyCode>
<FormattedPrice>$20.90</FormattedPrice>
 </Price>
 <AmountSaved>
<Amount>3280</Amount>
<CurrencyCode>USD</CurrencyCode>
<FormattedPrice>$32.80</FormattedPrice>
 </AmountSaved>
<PercentageSaved>61</PercentageSaved>
<Availability>Usually ships in 24 hours</Availability>
 <AvailabilityAttributes>
<AvailabilityType>now</AvailabilityType>
<MinimumHours>0</MinimumHours>
<MaximumHours>0</MaximumHours>
 </AvailabilityAttributes>
<IsEligibleForSuperSaverShipping>1</IsEligibleForSuperSaverShipping>
 </OfferListing>
 </Offer>
 </Offers>
 </Item>
 <Item>
<ASIN>B00DI1H8B2</ASIN>
<DetailPageURL>http://www.amazon.com/Teenage-Mutant-Ninja-Turtles-Throwing/dp/B00DI1H8B2%3FSubscriptionId%3DAKIAIHMGKYWGXDTROKMA%26tag%3Dventry-20%26linkCode%3Dxm2%26camp%3D2025%26creative%3D165953%26creativeASIN%3DB00DI1H8B2</DetailPageURL>
 <ItemLinks>
 <ItemLink>
<Description>Technical Details</Description>
<URL>http://www.amazon.com/Teenage-Mutant-Ninja-Turtles-Throwing/dp/tech-data/B00DI1H8B2%3FSubscriptionId%3DAKIAIHMGKYWGXDTROKMA%26tag%3Dventry-20%26linkCode%3Dxm2%26camp%3D2025%26creative%3D386001%26creativeASIN%3DB00DI1H8B2</URL>
 </ItemLink>
 <ItemLink>
<Description>Add To Baby Registry</Description>
<URL>http://www.amazon.com/gp/registry/baby/add-item.html%3Fasin.0%3DB00DI1H8B2%26SubscriptionId%3DAKIAIHMGKYWGXDTROKMA%26tag%3Dventry-20%26linkCode%3Dxm2%26camp%3D2025%26creative%3D386001%26creativeASIN%3DB00DI1H8B2</URL>
 </ItemLink>
 <ItemLink>
<Description>Add To Wedding Registry</Description>
<URL>http://www.amazon.com/gp/registry/wedding/add-item.html%3Fasin.0%3DB00DI1H8B2%26SubscriptionId%3DAKIAIHMGKYWGXDTROKMA%26tag%3Dventry-20%26linkCode%3Dxm2%26camp%3D2025%26creative%3D386001%26creativeASIN%3DB00DI1H8B2</URL>
 </ItemLink>
 <ItemLink>
<Description>Add To Wishlist</Description>
<URL>http://www.amazon.com/gp/registry/wishlist/add-item.html%3Fasin.0%3DB00DI1H8B2%26SubscriptionId%3DAKIAIHMGKYWGXDTROKMA%26tag%3Dventry-20%26linkCode%3Dxm2%26camp%3D2025%26creative%3D386001%26creativeASIN%3DB00DI1H8B2</URL>
 </ItemLink>
 <ItemLink>
<Description>Tell A Friend</Description>
<URL>http://www.amazon.com/gp/pdp/taf/B00DI1H8B2%3FSubscriptionId%3DAKIAIHMGKYWGXDTROKMA%26tag%3Dventry-20%26linkCode%3Dxm2%26camp%3D2025%26creative%3D386001%26creativeASIN%3DB00DI1H8B2</URL>
 </ItemLink>
 <ItemLink>
<Description>All Customer Reviews</Description>
<URL>http://www.amazon.com/review/product/B00DI1H8B2%3FSubscriptionId%3DAKIAIHMGKYWGXDTROKMA%26tag%3Dventry-20%26linkCode%3Dxm2%26camp%3D2025%26creative%3D386001%26creativeASIN%3DB00DI1H8B2</URL>
 </ItemLink>
 <ItemLink>
<Description>All Offers</Description>
<URL>http://www.amazon.com/gp/offer-listing/B00DI1H8B2%3FSubscriptionId%3DAKIAIHMGKYWGXDTROKMA%26tag%3Dventry-20%26linkCode%3Dxm2%26camp%3D2025%26creative%3D386001%26creativeASIN%3DB00DI1H8B2</URL>
 </ItemLink>
 </ItemLinks>
 <SmallImage>
<URL>http://ecx.images-amazon.com/images/I/51PhRt4BSkL._SL75_.jpg</URL>
<Height Units="pixels">75</Height>
<Width Units="pixels">75</Width>
 </SmallImage>
 <MediumImage>
<URL>http://ecx.images-amazon.com/images/I/51PhRt4BSkL._SL160_.jpg</URL>
<Height Units="pixels">160</Height>
<Width Units="pixels">160</Width>
 </MediumImage>
 <LargeImage>
<URL>http://ecx.images-amazon.com/images/I/51PhRt4BSkL.jpg</URL>
<Height Units="pixels">500</Height>
<Width Units="pixels">500</Width>
 </LargeImage>
 <ImageSets>
 <ImageSet Category="variant">
 <SwatchImage>
<URL>http://ecx.images-amazon.com/images/I/51hG9khmgxL._SL30_.jpg</URL>
<Height Units="pixels">30</Height>
<Width Units="pixels">30</Width>
 </SwatchImage>
 <SmallImage>
<URL>http://ecx.images-amazon.com/images/I/51hG9khmgxL._SL75_.jpg</URL>
<Height Units="pixels">75</Height>
<Width Units="pixels">75</Width>
 </SmallImage>
 <ThumbnailImage>
<URL>http://ecx.images-amazon.com/images/I/51hG9khmgxL._SL75_.jpg</URL>
<Height Units="pixels">75</Height>
<Width Units="pixels">75</Width>
 </ThumbnailImage>
 <TinyImage>
<URL>http://ecx.images-amazon.com/images/I/51hG9khmgxL._SL110_.jpg</URL>
<Height Units="pixels">110</Height>
<Width Units="pixels">110</Width>
 </TinyImage>
 <MediumImage>
<URL>http://ecx.images-amazon.com/images/I/51hG9khmgxL._SL160_.jpg</URL>
<Height Units="pixels">160</Height>
<Width Units="pixels">160</Width>
 </MediumImage>
 <LargeImage>
<URL>http://ecx.images-amazon.com/images/I/51hG9khmgxL.jpg</URL>
<Height Units="pixels">500</Height>
<Width Units="pixels">500</Width>
 </LargeImage>
 </ImageSet>
 <ImageSet Category="primary">
 <SwatchImage>
<URL>http://ecx.images-amazon.com/images/I/51PhRt4BSkL._SL30_.jpg</URL>
<Height Units="pixels">30</Height>
<Width Units="pixels">30</Width>
 </SwatchImage>
 <SmallImage>
<URL>http://ecx.images-amazon.com/images/I/51PhRt4BSkL._SL75_.jpg</URL>
<Height Units="pixels">75</Height>
<Width Units="pixels">75</Width>
 </SmallImage>
 <ThumbnailImage>
<URL>http://ecx.images-amazon.com/images/I/51PhRt4BSkL._SL75_.jpg</URL>
<Height Units="pixels">75</Height>
<Width Units="pixels">75</Width>
 </ThumbnailImage>
 <TinyImage>
<URL>http://ecx.images-amazon.com/images/I/51PhRt4BSkL._SL110_.jpg</URL>
<Height Units="pixels">110</Height>
<Width Units="pixels">110</Width>
 </TinyImage>
 <MediumImage>
<URL>http://ecx.images-amazon.com/images/I/51PhRt4BSkL._SL160_.jpg</URL>
<Height Units="pixels">160</Height>
<Width Units="pixels">160</Width>
 </MediumImage>
 <LargeImage>
<URL>http://ecx.images-amazon.com/images/I/51PhRt4BSkL.jpg</URL>
<Height Units="pixels">500</Height>
<Width Units="pixels">500</Width>
 </LargeImage>
 </ImageSet>
 </ImageSets>
 <ItemAttributes>
<Manufacturer>Unique Party Favors</Manufacturer>
<ProductGroup>Kitchen</ProductGroup>
<Title>Teenage Mutant Ninja Turtles Foam Throwing Stars, 4 Count</Title>
 </ItemAttributes>
 <OfferSummary>
 <LowestNewPrice>
<Amount>167</Amount>
<CurrencyCode>USD</CurrencyCode>
<FormattedPrice>$1.67</FormattedPrice>
 </LowestNewPrice>
<TotalNew>20</TotalNew>
<TotalUsed>0</TotalUsed>
<TotalCollectible>0</TotalCollectible>
<TotalRefurbished>0</TotalRefurbished>
 </OfferSummary>
 <Offers>
<TotalOffers>1</TotalOffers>
<TotalOfferPages>1</TotalOfferPages>
<MoreOffersUrl>http://www.amazon.com/gp/offer-listing/B00DI1H8B2%3FSubscriptionId%3DAKIAIHMGKYWGXDTROKMA%26tag%3Dventry-20%26linkCode%3Dxm2%26camp%3D2025%26creative%3D386001%26creativeASIN%3DB00DI1H8B2</MoreOffersUrl>
 <Offer>
<OfferAttributes>
<Condition>New</Condition>
</OfferAttributes>
 <OfferListing>
<OfferListingId>EZgDq7ciDsdqR2SgYS%2FgFEsVATGADrhCvF4EwLnr4069oUosmEhtDtNI1yRJrq%2BixU2XhOoBAH%2Fi11dytT4Oj5Y96YJYHx%2Bk9BqVyVxzBAbXeHHgAKp4GA%3D%3D</OfferListingId>
 <Price>
<Amount>279</Amount>
<CurrencyCode>USD</CurrencyCode>
<FormattedPrice>$2.79</FormattedPrice>
 </Price>
<Availability>Usually ships in 24 hours</Availability>
 <AvailabilityAttributes>
<AvailabilityType>now</AvailabilityType>
<MinimumHours>0</MinimumHours>
<MaximumHours>0</MaximumHours>
 </AvailabilityAttributes>
<IsEligibleForSuperSaverShipping>1</IsEligibleForSuperSaverShipping>
 </OfferListing>
 </Offer>
 </Offers>
 </Item>
 <Item>
<ASIN>B00E3DXN04</ASIN>
<DetailPageURL>http://www.amazon.com/Funny-Desk-Plate-Boss-Gift/dp/B00E3DXN04%3FSubscriptionId%3DAKIAIHMGKYWGXDTROKMA%26tag%3Dventry-20%26linkCode%3Dxm2%26camp%3D2025%26creative%3D165953%26creativeASIN%3DB00E3DXN04</DetailPageURL>
 <ItemLinks>
 <ItemLink>
<Description>Technical Details</Description>
<URL>http://www.amazon.com/Funny-Desk-Plate-Boss-Gift/dp/tech-data/B00E3DXN04%3FSubscriptionId%3DAKIAIHMGKYWGXDTROKMA%26tag%3Dventry-20%26linkCode%3Dxm2%26camp%3D2025%26creative%3D386001%26creativeASIN%3DB00E3DXN04</URL>
 </ItemLink>
 <ItemLink>
<Description>Add To Baby Registry</Description>
<URL>http://www.amazon.com/gp/registry/baby/add-item.html%3Fasin.0%3DB00E3DXN04%26SubscriptionId%3DAKIAIHMGKYWGXDTROKMA%26tag%3Dventry-20%26linkCode%3Dxm2%26camp%3D2025%26creative%3D386001%26creativeASIN%3DB00E3DXN04</URL>
 </ItemLink>
 <ItemLink>
<Description>Add To Wedding Registry</Description>
<URL>http://www.amazon.com/gp/registry/wedding/add-item.html%3Fasin.0%3DB00E3DXN04%26SubscriptionId%3DAKIAIHMGKYWGXDTROKMA%26tag%3Dventry-20%26linkCode%3Dxm2%26camp%3D2025%26creative%3D386001%26creativeASIN%3DB00E3DXN04</URL>
 </ItemLink>
 <ItemLink>
<Description>Add To Wishlist</Description>
<URL>http://www.amazon.com/gp/registry/wishlist/add-item.html%3Fasin.0%3DB00E3DXN04%26SubscriptionId%3DAKIAIHMGKYWGXDTROKMA%26tag%3Dventry-20%26linkCode%3Dxm2%26camp%3D2025%26creative%3D386001%26creativeASIN%3DB00E3DXN04</URL>
 </ItemLink>
 <ItemLink>
<Description>Tell A Friend</Description>
<URL>http://www.amazon.com/gp/pdp/taf/B00E3DXN04%3FSubscriptionId%3DAKIAIHMGKYWGXDTROKMA%26tag%3Dventry-20%26linkCode%3Dxm2%26camp%3D2025%26creative%3D386001%26creativeASIN%3DB00E3DXN04</URL>
 </ItemLink>
 <ItemLink>
<Description>All Customer Reviews</Description>
<URL>http://www.amazon.com/review/product/B00E3DXN04%3FSubscriptionId%3DAKIAIHMGKYWGXDTROKMA%26tag%3Dventry-20%26linkCode%3Dxm2%26camp%3D2025%26creative%3D386001%26creativeASIN%3DB00E3DXN04</URL>
 </ItemLink>
 <ItemLink>
<Description>All Offers</Description>
<URL>http://www.amazon.com/gp/offer-listing/B00E3DXN04%3FSubscriptionId%3DAKIAIHMGKYWGXDTROKMA%26tag%3Dventry-20%26linkCode%3Dxm2%26camp%3D2025%26creative%3D386001%26creativeASIN%3DB00E3DXN04</URL>
 </ItemLink>
 </ItemLinks>
 <SmallImage>
<URL>http://ecx.images-amazon.com/images/I/41r91O7fz3L._SL75_.jpg</URL>
<Height Units="pixels">60</Height>
<Width Units="pixels">75</Width>
 </SmallImage>
 <MediumImage>
<URL>http://ecx.images-amazon.com/images/I/41r91O7fz3L._SL160_.jpg</URL>
<Height Units="pixels">128</Height>
<Width Units="pixels">160</Width>
 </MediumImage>
 <LargeImage>
<URL>http://ecx.images-amazon.com/images/I/41r91O7fz3L.jpg</URL>
<Height Units="pixels">400</Height>
<Width Units="pixels">500</Width>
 </LargeImage>
 <ImageSets>
 <ImageSet Category="variant">
 <SwatchImage>
<URL>http://ecx.images-amazon.com/images/I/51aiLLrYqVL._SL30_.jpg</URL>
<Height Units="pixels">23</Height>
<Width Units="pixels">30</Width>
 </SwatchImage>
 <SmallImage>
<URL>http://ecx.images-amazon.com/images/I/51aiLLrYqVL._SL75_.jpg</URL>
<Height Units="pixels">58</Height>
<Width Units="pixels">75</Width>
 </SmallImage>
 <ThumbnailImage>
<URL>http://ecx.images-amazon.com/images/I/51aiLLrYqVL._SL75_.jpg</URL>
<Height Units="pixels">58</Height>
<Width Units="pixels">75</Width>
 </ThumbnailImage>
 <TinyImage>
<URL>http://ecx.images-amazon.com/images/I/51aiLLrYqVL._SL110_.jpg</URL>
<Height Units="pixels">85</Height>
<Width Units="pixels">110</Width>
 </TinyImage>
 <MediumImage>
<URL>http://ecx.images-amazon.com/images/I/51aiLLrYqVL._SL160_.jpg</URL>
<Height Units="pixels">123</Height>
<Width Units="pixels">160</Width>
 </MediumImage>
 <LargeImage>
<URL>http://ecx.images-amazon.com/images/I/51aiLLrYqVL.jpg</URL>
<Height Units="pixels">385</Height>
<Width Units="pixels">500</Width>
 </LargeImage>
 </ImageSet>
 <ImageSet Category="variant">
 <SwatchImage>
<URL>http://ecx.images-amazon.com/images/I/41AzbS1k4CL._SL30_.jpg</URL>
<Height Units="pixels">17</Height>
<Width Units="pixels">30</Width>
 </SwatchImage>
 <SmallImage>
<URL>http://ecx.images-amazon.com/images/I/41AzbS1k4CL._SL75_.jpg</URL>
<Height Units="pixels">42</Height>
<Width Units="pixels">75</Width>
 </SmallImage>
 <ThumbnailImage>
<URL>http://ecx.images-amazon.com/images/I/41AzbS1k4CL._SL75_.jpg</URL>
<Height Units="pixels">42</Height>
<Width Units="pixels">75</Width>
 </ThumbnailImage>
 <TinyImage>
<URL>http://ecx.images-amazon.com/images/I/41AzbS1k4CL._SL110_.jpg</URL>
<Height Units="pixels">62</Height>
<Width Units="pixels">110</Width>
 </TinyImage>
 <MediumImage>
<URL>http://ecx.images-amazon.com/images/I/41AzbS1k4CL._SL160_.jpg</URL>
<Height Units="pixels">90</Height>
<Width Units="pixels">160</Width>
 </MediumImage>
 <LargeImage>
<URL>http://ecx.images-amazon.com/images/I/41AzbS1k4CL.jpg</URL>
<Height Units="pixels">281</Height>
<Width Units="pixels">500</Width>
 </LargeImage>
 </ImageSet>
 <ImageSet Category="primary">
 <SwatchImage>
<URL>http://ecx.images-amazon.com/images/I/41r91O7fz3L._SL30_.jpg</URL>
<Height Units="pixels">24</Height>
<Width Units="pixels">30</Width>
 </SwatchImage>
 <SmallImage>
<URL>http://ecx.images-amazon.com/images/I/41r91O7fz3L._SL75_.jpg</URL>
<Height Units="pixels">60</Height>
<Width Units="pixels">75</Width>
 </SmallImage>
 <ThumbnailImage>
<URL>http://ecx.images-amazon.com/images/I/41r91O7fz3L._SL75_.jpg</URL>
<Height Units="pixels">60</Height>
<Width Units="pixels">75</Width>
 </ThumbnailImage>
 <TinyImage>
<URL>http://ecx.images-amazon.com/images/I/41r91O7fz3L._SL110_.jpg</URL>
<Height Units="pixels">88</Height>
<Width Units="pixels">110</Width>
 </TinyImage>
 <MediumImage>
<URL>http://ecx.images-amazon.com/images/I/41r91O7fz3L._SL160_.jpg</URL>
<Height Units="pixels">128</Height>
<Width Units="pixels">160</Width>
 </MediumImage>
 <LargeImage>
<URL>http://ecx.images-amazon.com/images/I/41r91O7fz3L.jpg</URL>
<Height Units="pixels">400</Height>
<Width Units="pixels">500</Width>
 </LargeImage>
 </ImageSet>
 </ImageSets>
 <ItemAttributes>
<Manufacturer>Holmes Stamp & Sign</Manufacturer>
<ProductGroup>Home</ProductGroup>
<Title>Funny Desk Plate for Boss - Gag Gift</Title>
 </ItemAttributes>
 <OfferSummary>
 <LowestNewPrice>
<Amount>1000</Amount>
<CurrencyCode>USD</CurrencyCode>
<FormattedPrice>$10.00</FormattedPrice>
 </LowestNewPrice>
<TotalNew>2</TotalNew>
<TotalUsed>0</TotalUsed>
<TotalCollectible>0</TotalCollectible>
<TotalRefurbished>0</TotalRefurbished>
 </OfferSummary>
 <Offers>
<TotalOffers>1</TotalOffers>
<TotalOfferPages>1</TotalOfferPages>
<MoreOffersUrl>http://www.amazon.com/gp/offer-listing/B00E3DXN04%3FSubscriptionId%3DAKIAIHMGKYWGXDTROKMA%26tag%3Dventry-20%26linkCode%3Dxm2%26camp%3D2025%26creative%3D386001%26creativeASIN%3DB00E3DXN04</MoreOffersUrl>
 <Offer>
<OfferAttributes>
<Condition>New</Condition>
</OfferAttributes>
 <OfferListing>
<OfferListingId>ZAtCoPXvrrXN5JkH7iRsyPFAy4any%2FrD1tyk7m%2FEjFj7jM2rB9D%2BQl3BqmOrmxhE%2BDqyGR8ShxCIyBIyyFoW0mpWP2qbC77g3zlfQpXtctjCygGc4iRggN0xv6kp6sJidVdZo6lrsOpecT1nPYI%2FPA%3D%3D</OfferListingId>
 <Price>
<Amount>1495</Amount>
<CurrencyCode>USD</CurrencyCode>
<FormattedPrice>$14.95</FormattedPrice>
 </Price>
<Availability>Usually ships in 1-2 business days</Availability>
 <AvailabilityAttributes>
<AvailabilityType>now</AvailabilityType>
<MinimumHours>24</MinimumHours>
<MaximumHours>48</MaximumHours>
 </AvailabilityAttributes>
<IsEligibleForSuperSaverShipping>0</IsEligibleForSuperSaverShipping>
 </OfferListing>
 </Offer>
 </Offers>
 </Item>
 <Item>
<ASIN>B00A2UUJRW</ASIN>
<DetailPageURL>http://www.amazon.com/ThinkGeek-Floppy-Disk-Drink-Coasters/dp/B00A2UUJRW%3FSubscriptionId%3DAKIAIHMGKYWGXDTROKMA%26tag%3Dventry-20%26linkCode%3Dxm2%26camp%3D2025%26creative%3D165953%26creativeASIN%3DB00A2UUJRW</DetailPageURL>
 <ItemLinks>
 <ItemLink>
<Description>Technical Details</Description>
<URL>http://www.amazon.com/ThinkGeek-Floppy-Disk-Drink-Coasters/dp/tech-data/B00A2UUJRW%3FSubscriptionId%3DAKIAIHMGKYWGXDTROKMA%26tag%3Dventry-20%26linkCode%3Dxm2%26camp%3D2025%26creative%3D386001%26creativeASIN%3DB00A2UUJRW</URL>
 </ItemLink>
 <ItemLink>
<Description>Add To Baby Registry</Description>
<URL>http://www.amazon.com/gp/registry/baby/add-item.html%3Fasin.0%3DB00A2UUJRW%26SubscriptionId%3DAKIAIHMGKYWGXDTROKMA%26tag%3Dventry-20%26linkCode%3Dxm2%26camp%3D2025%26creative%3D386001%26creativeASIN%3DB00A2UUJRW</URL>
 </ItemLink>
 <ItemLink>
<Description>Add To Wedding Registry</Description>
<URL>http://www.amazon.com/gp/registry/wedding/add-item.html%3Fasin.0%3DB00A2UUJRW%26SubscriptionId%3DAKIAIHMGKYWGXDTROKMA%26tag%3Dventry-20%26linkCode%3Dxm2%26camp%3D2025%26creative%3D386001%26creativeASIN%3DB00A2UUJRW</URL>
 </ItemLink>
 <ItemLink>
<Description>Add To Wishlist</Description>
<URL>http://www.amazon.com/gp/registry/wishlist/add-item.html%3Fasin.0%3DB00A2UUJRW%26SubscriptionId%3DAKIAIHMGKYWGXDTROKMA%26tag%3Dventry-20%26linkCode%3Dxm2%26camp%3D2025%26creative%3D386001%26creativeASIN%3DB00A2UUJRW</URL>
 </ItemLink>
 <ItemLink>
<Description>Tell A Friend</Description>
<URL>http://www.amazon.com/gp/pdp/taf/B00A2UUJRW%3FSubscriptionId%3DAKIAIHMGKYWGXDTROKMA%26tag%3Dventry-20%26linkCode%3Dxm2%26camp%3D2025%26creative%3D386001%26creativeASIN%3DB00A2UUJRW</URL>
 </ItemLink>
 <ItemLink>
<Description>All Customer Reviews</Description>
<URL>http://www.amazon.com/review/product/B00A2UUJRW%3FSubscriptionId%3DAKIAIHMGKYWGXDTROKMA%26tag%3Dventry-20%26linkCode%3Dxm2%26camp%3D2025%26creative%3D386001%26creativeASIN%3DB00A2UUJRW</URL>
 </ItemLink>
 <ItemLink>
<Description>All Offers</Description>
<URL>http://www.amazon.com/gp/offer-listing/B00A2UUJRW%3FSubscriptionId%3DAKIAIHMGKYWGXDTROKMA%26tag%3Dventry-20%26linkCode%3Dxm2%26camp%3D2025%26creative%3D386001%26creativeASIN%3DB00A2UUJRW</URL>
 </ItemLink>
 </ItemLinks>
 <SmallImage>
<URL>http://ecx.images-amazon.com/images/I/51JlpBqvENL._SL75_.jpg</URL>
<Height Units="pixels">75</Height>
<Width Units="pixels">75</Width>
 </SmallImage>
 <MediumImage>
<URL>http://ecx.images-amazon.com/images/I/51JlpBqvENL._SL160_.jpg</URL>
<Height Units="pixels">160</Height>
<Width Units="pixels">160</Width>
 </MediumImage>
 <LargeImage>
<URL>http://ecx.images-amazon.com/images/I/51JlpBqvENL.jpg</URL>
<Height Units="pixels">500</Height>
<Width Units="pixels">500</Width>
 </LargeImage>
<ImageSets>
 <ImageSet Category="primary">
 <SwatchImage>
<URL>http://ecx.images-amazon.com/images/I/51JlpBqvENL._SL30_.jpg</URL>
<Height Units="pixels">30</Height>
<Width Units="pixels">30</Width>
 </SwatchImage>
 <SmallImage>
<URL>http://ecx.images-amazon.com/images/I/51JlpBqvENL._SL75_.jpg</URL>
<Height Units="pixels">75</Height>
<Width Units="pixels">75</Width>
 </SmallImage>
 <ThumbnailImage>
<URL>http://ecx.images-amazon.com/images/I/51JlpBqvENL._SL75_.jpg</URL>
<Height Units="pixels">75</Height>
<Width Units="pixels">75</Width>
 </ThumbnailImage>
 <TinyImage>
<URL>http://ecx.images-amazon.com/images/I/51JlpBqvENL._SL110_.jpg</URL>
<Height Units="pixels">110</Height>
<Width Units="pixels">110</Width>
 </TinyImage>
 <MediumImage>
<URL>http://ecx.images-amazon.com/images/I/51JlpBqvENL._SL160_.jpg</URL>
<Height Units="pixels">160</Height>
<Width Units="pixels">160</Width>
 </MediumImage>
 <LargeImage>
<URL>http://ecx.images-amazon.com/images/I/51JlpBqvENL.jpg</URL>
<Height Units="pixels">500</Height>
<Width Units="pixels">500</Width>
 </LargeImage>
 </ImageSet>
</ImageSets>
 <ItemAttributes>
<Manufacturer>ThinkGeek</Manufacturer>
<ProductGroup>Kitchen</ProductGroup>
<Title>Floppy Disk Drink Coasters</Title>
 </ItemAttributes>
 <OfferSummary>
 <LowestNewPrice>
<Amount>1173</Amount>
<CurrencyCode>USD</CurrencyCode>
<FormattedPrice>$11.73</FormattedPrice>
 </LowestNewPrice>
<TotalNew>2</TotalNew>
<TotalUsed>0</TotalUsed>
<TotalCollectible>0</TotalCollectible>
<TotalRefurbished>0</TotalRefurbished>
 </OfferSummary>
 <Offers>
<TotalOffers>1</TotalOffers>
<TotalOfferPages>1</TotalOfferPages>
<MoreOffersUrl>http://www.amazon.com/gp/offer-listing/B00A2UUJRW%3FSubscriptionId%3DAKIAIHMGKYWGXDTROKMA%26tag%3Dventry-20%26linkCode%3Dxm2%26camp%3D2025%26creative%3D386001%26creativeASIN%3DB00A2UUJRW</MoreOffersUrl>
 <Offer>
<OfferAttributes>
<Condition>New</Condition>
</OfferAttributes>
 <OfferListing>
<OfferListingId>tKsNDfFfz8SITWruIGtkFFIdcMAUoqKZ1CM9XBaPee6Gh6P3Dw6o29JYl2d0QH92GpFYw%2FORn5wZAuyi9dudraJIsjWqpesvNBpgj%2F%2Bsyipm6Td%2BbdtLXG3dY%2BPt%2FOIF7%2B4oA%2Brm5s5C%2BKHuA03foKXgB6t6TgwZ</OfferListingId>
 <Price>
<Amount>1178</Amount>
<CurrencyCode>USD</CurrencyCode>
<FormattedPrice>$11.78</FormattedPrice>
 </Price>
<Availability>Usually ships in 24 hours</Availability>
 <AvailabilityAttributes>
<AvailabilityType>now</AvailabilityType>
<MinimumHours>0</MinimumHours>
<MaximumHours>0</MaximumHours>
 </AvailabilityAttributes>
<IsEligibleForSuperSaverShipping>1</IsEligibleForSuperSaverShipping>
 </OfferListing>
 </Offer>
 </Offers>
 </Item>
 <Item>
<ASIN>B00N36C6BE</ASIN>
<DetailPageURL>http://www.amazon.com/Never-Have-Ever-Game-Decisions/dp/B00N36C6BE%3FSubscriptionId%3DAKIAIHMGKYWGXDTROKMA%26tag%3Dventry-20%26linkCode%3Dxm2%26camp%3D2025%26creative%3D165953%26creativeASIN%3DB00N36C6BE</DetailPageURL>
 <ItemLinks>
 <ItemLink>
<Description>Technical Details</Description>
<URL>http://www.amazon.com/Never-Have-Ever-Game-Decisions/dp/tech-data/B00N36C6BE%3FSubscriptionId%3DAKIAIHMGKYWGXDTROKMA%26tag%3Dventry-20%26linkCode%3Dxm2%26camp%3D2025%26creative%3D386001%26creativeASIN%3DB00N36C6BE</URL>
 </ItemLink>
 <ItemLink>
<Description>Add To Baby Registry</Description>
<URL>http://www.amazon.com/gp/registry/baby/add-item.html%3Fasin.0%3DB00N36C6BE%26SubscriptionId%3DAKIAIHMGKYWGXDTROKMA%26tag%3Dventry-20%26linkCode%3Dxm2%26camp%3D2025%26creative%3D386001%26creativeASIN%3DB00N36C6BE</URL>
 </ItemLink>
 <ItemLink>
<Description>Add To Wedding Registry</Description>
<URL>http://www.amazon.com/gp/registry/wedding/add-item.html%3Fasin.0%3DB00N36C6BE%26SubscriptionId%3DAKIAIHMGKYWGXDTROKMA%26tag%3Dventry-20%26linkCode%3Dxm2%26camp%3D2025%26creative%3D386001%26creativeASIN%3DB00N36C6BE</URL>
 </ItemLink>
 <ItemLink>
<Description>Add To Wishlist</Description>
<URL>http://www.amazon.com/gp/registry/wishlist/add-item.html%3Fasin.0%3DB00N36C6BE%26SubscriptionId%3DAKIAIHMGKYWGXDTROKMA%26tag%3Dventry-20%26linkCode%3Dxm2%26camp%3D2025%26creative%3D386001%26creativeASIN%3DB00N36C6BE</URL>
 </ItemLink>
 <ItemLink>
<Description>Tell A Friend</Description>
<URL>http://www.amazon.com/gp/pdp/taf/B00N36C6BE%3FSubscriptionId%3DAKIAIHMGKYWGXDTROKMA%26tag%3Dventry-20%26linkCode%3Dxm2%26camp%3D2025%26creative%3D386001%26creativeASIN%3DB00N36C6BE</URL>
 </ItemLink>
 <ItemLink>
<Description>All Customer Reviews</Description>
<URL>http://www.amazon.com/review/product/B00N36C6BE%3FSubscriptionId%3DAKIAIHMGKYWGXDTROKMA%26tag%3Dventry-20%26linkCode%3Dxm2%26camp%3D2025%26creative%3D386001%26creativeASIN%3DB00N36C6BE</URL>
 </ItemLink>
 <ItemLink>
<Description>All Offers</Description>
<URL>http://www.amazon.com/gp/offer-listing/B00N36C6BE%3FSubscriptionId%3DAKIAIHMGKYWGXDTROKMA%26tag%3Dventry-20%26linkCode%3Dxm2%26camp%3D2025%26creative%3D386001%26creativeASIN%3DB00N36C6BE</URL>
 </ItemLink>
 </ItemLinks>
 <SmallImage>
<URL>http://ecx.images-amazon.com/images/I/41pCw0HMLoL._SL75_.jpg</URL>
<Height Units="pixels">75</Height>
<Width Units="pixels">59</Width>
 </SmallImage>
 <MediumImage>
<URL>http://ecx.images-amazon.com/images/I/41pCw0HMLoL._SL160_.jpg</URL>
<Height Units="pixels">160</Height>
<Width Units="pixels">126</Width>
 </MediumImage>
 <LargeImage>
<URL>http://ecx.images-amazon.com/images/I/41pCw0HMLoL.jpg</URL>
<Height Units="pixels">500</Height>
<Width Units="pixels">393</Width>
 </LargeImage>
 <ImageSets>
 <ImageSet Category="variant">
 <SwatchImage>
<URL>http://ecx.images-amazon.com/images/I/51Hkt37ML4L._SL30_.jpg</URL>
<Height Units="pixels">22</Height>
<Width Units="pixels">30</Width>
 </SwatchImage>
 <SmallImage>
<URL>http://ecx.images-amazon.com/images/I/51Hkt37ML4L._SL75_.jpg</URL>
<Height Units="pixels">56</Height>
<Width Units="pixels">75</Width>
 </SmallImage>
 <ThumbnailImage>
<URL>http://ecx.images-amazon.com/images/I/51Hkt37ML4L._SL75_.jpg</URL>
<Height Units="pixels">56</Height>
<Width Units="pixels">75</Width>
 </ThumbnailImage>
 <TinyImage>
<URL>http://ecx.images-amazon.com/images/I/51Hkt37ML4L._SL110_.jpg</URL>
<Height Units="pixels">82</Height>
<Width Units="pixels">110</Width>
 </TinyImage>
 <MediumImage>
<URL>http://ecx.images-amazon.com/images/I/51Hkt37ML4L._SL160_.jpg</URL>
<Height Units="pixels">119</Height>
<Width Units="pixels">160</Width>
 </MediumImage>
 <LargeImage>
<URL>http://ecx.images-amazon.com/images/I/51Hkt37ML4L.jpg</URL>
<Height Units="pixels">372</Height>
<Width Units="pixels">500</Width>
 </LargeImage>
 </ImageSet>
 <ImageSet Category="variant">
 <SwatchImage>
<URL>http://ecx.images-amazon.com/images/I/51bFBuO1guL._SL30_.jpg</URL>
<Height Units="pixels">24</Height>
<Width Units="pixels">30</Width>
 </SwatchImage>
 <SmallImage>
<URL>http://ecx.images-amazon.com/images/I/51bFBuO1guL._SL75_.jpg</URL>
<Height Units="pixels">59</Height>
<Width Units="pixels">75</Width>
 </SmallImage>
 <ThumbnailImage>
<URL>http://ecx.images-amazon.com/images/I/51bFBuO1guL._SL75_.jpg</URL>
<Height Units="pixels">59</Height>
<Width Units="pixels">75</Width>
 </ThumbnailImage>
 <TinyImage>
<URL>http://ecx.images-amazon.com/images/I/51bFBuO1guL._SL110_.jpg</URL>
<Height Units="pixels">87</Height>
<Width Units="pixels">110</Width>
 </TinyImage>
 <MediumImage>
<URL>http://ecx.images-amazon.com/images/I/51bFBuO1guL._SL160_.jpg</URL>
<Height Units="pixels">126</Height>
<Width Units="pixels">160</Width>
 </MediumImage>
 <LargeImage>
<URL>http://ecx.images-amazon.com/images/I/51bFBuO1guL.jpg</URL>
<Height Units="pixels">394</Height>
<Width Units="pixels">500</Width>
 </LargeImage>
 </ImageSet>
 <ImageSet Category="variant">
 <SwatchImage>
<URL>http://ecx.images-amazon.com/images/I/51T5uAf4gXL._SL30_.jpg</URL>
<Height Units="pixels">28</Height>
<Width Units="pixels">30</Width>
 </SwatchImage>
 <SmallImage>
<URL>http://ecx.images-amazon.com/images/I/51T5uAf4gXL._SL75_.jpg</URL>
<Height Units="pixels">69</Height>
<Width Units="pixels">75</Width>
 </SmallImage>
 <ThumbnailImage>
<URL>http://ecx.images-amazon.com/images/I/51T5uAf4gXL._SL75_.jpg</URL>
<Height Units="pixels">69</Height>
<Width Units="pixels">75</Width>
 </ThumbnailImage>
 <TinyImage>
<URL>http://ecx.images-amazon.com/images/I/51T5uAf4gXL._SL110_.jpg</URL>
<Height Units="pixels">102</Height>
<Width Units="pixels">110</Width>
 </TinyImage>
 <MediumImage>
<URL>http://ecx.images-amazon.com/images/I/51T5uAf4gXL._SL160_.jpg</URL>
<Height Units="pixels">148</Height>
<Width Units="pixels">160</Width>
 </MediumImage>
 <LargeImage>
<URL>http://ecx.images-amazon.com/images/I/51T5uAf4gXL.jpg</URL>
<Height Units="pixels">463</Height>
<Width Units="pixels">500</Width>
 </LargeImage>
 </ImageSet>
 <ImageSet Category="variant">
 <SwatchImage>
<URL>http://ecx.images-amazon.com/images/I/41Z2I1p5zqL._SL30_.jpg</URL>
<Height Units="pixels">19</Height>
<Width Units="pixels">30</Width>
 </SwatchImage>
 <SmallImage>
<URL>http://ecx.images-amazon.com/images/I/41Z2I1p5zqL._SL75_.jpg</URL>
<Height Units="pixels">47</Height>
<Width Units="pixels">75</Width>
 </SmallImage>
 <ThumbnailImage>
<URL>http://ecx.images-amazon.com/images/I/41Z2I1p5zqL._SL75_.jpg</URL>
<Height Units="pixels">47</Height>
<Width Units="pixels">75</Width>
 </ThumbnailImage>
 <TinyImage>
<URL>http://ecx.images-amazon.com/images/I/41Z2I1p5zqL._SL110_.jpg</URL>
<Height Units="pixels">69</Height>
<Width Units="pixels">110</Width>
 </TinyImage>
 <MediumImage>
<URL>http://ecx.images-amazon.com/images/I/41Z2I1p5zqL._SL160_.jpg</URL>
<Height Units="pixels">100</Height>
<Width Units="pixels">160</Width>
 </MediumImage>
 <LargeImage>
<URL>http://ecx.images-amazon.com/images/I/41Z2I1p5zqL.jpg</URL>
<Height Units="pixels">314</Height>
<Width Units="pixels">500</Width>
 </LargeImage>
 </ImageSet>
 <ImageSet Category="variant">
 <SwatchImage>
<URL>http://ecx.images-amazon.com/images/I/51S%2Bg4WjxuL._SL30_.jpg</URL>
<Height Units="pixels">28</Height>
<Width Units="pixels">30</Width>
 </SwatchImage>
 <SmallImage>
<URL>http://ecx.images-amazon.com/images/I/51S%2Bg4WjxuL._SL75_.jpg</URL>
<Height Units="pixels">71</Height>
<Width Units="pixels">75</Width>
 </SmallImage>
 <ThumbnailImage>
<URL>http://ecx.images-amazon.com/images/I/51S%2Bg4WjxuL._SL75_.jpg</URL>
<Height Units="pixels">71</Height>
<Width Units="pixels">75</Width>
 </ThumbnailImage>
 <TinyImage>
<URL>http://ecx.images-amazon.com/images/I/51S%2Bg4WjxuL._SL110_.jpg</URL>
<Height Units="pixels">104</Height>
<Width Units="pixels">110</Width>
 </TinyImage>
 <MediumImage>
<URL>http://ecx.images-amazon.com/images/I/51S%2Bg4WjxuL._SL160_.jpg</URL>
<Height Units="pixels">152</Height>
<Width Units="pixels">160</Width>
 </MediumImage>
 <LargeImage>
<URL>http://ecx.images-amazon.com/images/I/51S%2Bg4WjxuL.jpg</URL>
<Height Units="pixels">475</Height>
<Width Units="pixels">500</Width>
 </LargeImage>
 </ImageSet>
 <ImageSet Category="variant">
 <SwatchImage>
<URL>http://ecx.images-amazon.com/images/I/51QSs57wkWL._SL30_.jpg</URL>
<Height Units="pixels">21</Height>
<Width Units="pixels">30</Width>
 </SwatchImage>
 <SmallImage>
<URL>http://ecx.images-amazon.com/images/I/51QSs57wkWL._SL75_.jpg</URL>
<Height Units="pixels">53</Height>
<Width Units="pixels">75</Width>
 </SmallImage>
 <ThumbnailImage>
<URL>http://ecx.images-amazon.com/images/I/51QSs57wkWL._SL75_.jpg</URL>
<Height Units="pixels">53</Height>
<Width Units="pixels">75</Width>
 </ThumbnailImage>
 <TinyImage>
<URL>http://ecx.images-amazon.com/images/I/51QSs57wkWL._SL110_.jpg</URL>
<Height Units="pixels">77</Height>
<Width Units="pixels">110</Width>
 </TinyImage>
 <MediumImage>
<URL>http://ecx.images-amazon.com/images/I/51QSs57wkWL._SL160_.jpg</URL>
<Height Units="pixels">112</Height>
<Width Units="pixels">160</Width>
 </MediumImage>
 <LargeImage>
<URL>http://ecx.images-amazon.com/images/I/51QSs57wkWL.jpg</URL>
<Height Units="pixels">351</Height>
<Width Units="pixels">500</Width>
 </LargeImage>
 </ImageSet>
 <ImageSet Category="primary">
 <SwatchImage>
<URL>http://ecx.images-amazon.com/images/I/41pCw0HMLoL._SL30_.jpg</URL>
<Height Units="pixels">30</Height>
<Width Units="pixels">24</Width>
 </SwatchImage>
 <SmallImage>
<URL>http://ecx.images-amazon.com/images/I/41pCw0HMLoL._SL75_.jpg</URL>
<Height Units="pixels">75</Height>
<Width Units="pixels">59</Width>
 </SmallImage>
 <ThumbnailImage>
<URL>http://ecx.images-amazon.com/images/I/41pCw0HMLoL._SL75_.jpg</URL>
<Height Units="pixels">75</Height>
<Width Units="pixels">59</Width>
 </ThumbnailImage>
 <TinyImage>
<URL>http://ecx.images-amazon.com/images/I/41pCw0HMLoL._SL110_.jpg</URL>
<Height Units="pixels">110</Height>
<Width Units="pixels">86</Width>
 </TinyImage>
 <MediumImage>
<URL>http://ecx.images-amazon.com/images/I/41pCw0HMLoL._SL160_.jpg</URL>
<Height Units="pixels">160</Height>
<Width Units="pixels">126</Width>
 </MediumImage>
 <LargeImage>
<URL>http://ecx.images-amazon.com/images/I/41pCw0HMLoL.jpg</URL>
<Height Units="pixels">500</Height>
<Width Units="pixels">393</Width>
 </LargeImage>
 </ImageSet>
 </ImageSets>
 <ItemAttributes>
<Manufacturer>INI, LLC</Manufacturer>
<ProductGroup>Toy</ProductGroup>
<Title>Never Have I Ever, the Game of Poor Life Decisions - Only Get this Card Game if You Want Tears Running Down Your Face from Gut Busting Laughs, Outrageous Fun and to Be The Hit of Every Party From This Day Forward. Not for the Faint of Heart. Played on The Ellen DeGeneres Show.</Title>
 </ItemAttributes>
 <OfferSummary>
 <LowestNewPrice>
<Amount>2500</Amount>
<CurrencyCode>USD</CurrencyCode>
<FormattedPrice>$25.00</FormattedPrice>
 </LowestNewPrice>
<TotalNew>1</TotalNew>
<TotalUsed>0</TotalUsed>
<TotalCollectible>0</TotalCollectible>
<TotalRefurbished>0</TotalRefurbished>
 </OfferSummary>
 <Offers>
<TotalOffers>1</TotalOffers>
<TotalOfferPages>1</TotalOfferPages>
<MoreOffersUrl>http://www.amazon.com/gp/offer-listing/B00N36C6BE%3FSubscriptionId%3DAKIAIHMGKYWGXDTROKMA%26tag%3Dventry-20%26linkCode%3Dxm2%26camp%3D2025%26creative%3D386001%26creativeASIN%3DB00N36C6BE</MoreOffersUrl>
 <Offer>
<OfferAttributes>
<Condition>New</Condition>
</OfferAttributes>
 <OfferListing>
<OfferListingId>ShpFwfmlMCToACKEby%2FfInnsfFdVv%2B8DCo6SZXnx59oA1hb9xfNhLZ3SMOijw3ZSgDOxiDjQg3QFGwwygdJ5BZ5oZy65ZPu6wg0G4GKWBfkHBTGk%2BdXOkDqUsNOVAhBF9xse2zVKS6ES90WwEmAp%2FA7%2BamIswA%2FJ</OfferListingId>
 <Price>
<Amount>2500</Amount>
<CurrencyCode>USD</CurrencyCode>
<FormattedPrice>$25.00</FormattedPrice>
 </Price>
<Availability>Usually ships in 24 hours</Availability>
 <AvailabilityAttributes>
<AvailabilityType>now</AvailabilityType>
<MinimumHours>0</MinimumHours>
<MaximumHours>0</MaximumHours>
 </AvailabilityAttributes>
<IsEligibleForSuperSaverShipping>1</IsEligibleForSuperSaverShipping>
 </OfferListing>
 </Offer>
 </Offers>
 </Item>
 <Item>
<ASIN>B00MMHUZWW</ASIN>
<DetailPageURL>http://www.amazon.com/FunAir-Gaga-Ball-Pit/dp/B00MMHUZWW%3FSubscriptionId%3DAKIAIHMGKYWGXDTROKMA%26tag%3Dventry-20%26linkCode%3Dxm2%26camp%3D2025%26creative%3D165953%26creativeASIN%3DB00MMHUZWW</DetailPageURL>
 <ItemLinks>
 <ItemLink>
<Description>Technical Details</Description>
<URL>http://www.amazon.com/FunAir-Gaga-Ball-Pit/dp/tech-data/B00MMHUZWW%3FSubscriptionId%3DAKIAIHMGKYWGXDTROKMA%26tag%3Dventry-20%26linkCode%3Dxm2%26camp%3D2025%26creative%3D386001%26creativeASIN%3DB00MMHUZWW</URL>
 </ItemLink>
 <ItemLink>
<Description>Add To Baby Registry</Description>
<URL>http://www.amazon.com/gp/registry/baby/add-item.html%3Fasin.0%3DB00MMHUZWW%26SubscriptionId%3DAKIAIHMGKYWGXDTROKMA%26tag%3Dventry-20%26linkCode%3Dxm2%26camp%3D2025%26creative%3D386001%26creativeASIN%3DB00MMHUZWW</URL>
 </ItemLink>
 <ItemLink>
<Description>Add To Wedding Registry</Description>
<URL>http://www.amazon.com/gp/registry/wedding/add-item.html%3Fasin.0%3DB00MMHUZWW%26SubscriptionId%3DAKIAIHMGKYWGXDTROKMA%26tag%3Dventry-20%26linkCode%3Dxm2%26camp%3D2025%26creative%3D386001%26creativeASIN%3DB00MMHUZWW</URL>
 </ItemLink>
 <ItemLink>
<Description>Add To Wishlist</Description>
<URL>http://www.amazon.com/gp/registry/wishlist/add-item.html%3Fasin.0%3DB00MMHUZWW%26SubscriptionId%3DAKIAIHMGKYWGXDTROKMA%26tag%3Dventry-20%26linkCode%3Dxm2%26camp%3D2025%26creative%3D386001%26creativeASIN%3DB00MMHUZWW</URL>
 </ItemLink>
 <ItemLink>
<Description>Tell A Friend</Description>
<URL>http://www.amazon.com/gp/pdp/taf/B00MMHUZWW%3FSubscriptionId%3DAKIAIHMGKYWGXDTROKMA%26tag%3Dventry-20%26linkCode%3Dxm2%26camp%3D2025%26creative%3D386001%26creativeASIN%3DB00MMHUZWW</URL>
 </ItemLink>
 <ItemLink>
<Description>All Customer Reviews</Description>
<URL>http://www.amazon.com/review/product/B00MMHUZWW%3FSubscriptionId%3DAKIAIHMGKYWGXDTROKMA%26tag%3Dventry-20%26linkCode%3Dxm2%26camp%3D2025%26creative%3D386001%26creativeASIN%3DB00MMHUZWW</URL>
 </ItemLink>
 <ItemLink>
<Description>All Offers</Description>
<URL>http://www.amazon.com/gp/offer-listing/B00MMHUZWW%3FSubscriptionId%3DAKIAIHMGKYWGXDTROKMA%26tag%3Dventry-20%26linkCode%3Dxm2%26camp%3D2025%26creative%3D386001%26creativeASIN%3DB00MMHUZWW</URL>
 </ItemLink>
 </ItemLinks>
 <SmallImage>
<URL>http://ecx.images-amazon.com/images/I/616QzGUuq4L._SL75_.jpg</URL>
<Height Units="pixels">56</Height>
<Width Units="pixels">75</Width>
 </SmallImage>
 <MediumImage>
<URL>http://ecx.images-amazon.com/images/I/616QzGUuq4L._SL160_.jpg</URL>
<Height Units="pixels">120</Height>
<Width Units="pixels">160</Width>
 </MediumImage>
 <LargeImage>
<URL>http://ecx.images-amazon.com/images/I/616QzGUuq4L.jpg</URL>
<Height Units="pixels">375</Height>
<Width Units="pixels">500</Width>
 </LargeImage>
 <ImageSets>
 <ImageSet Category="variant">
 <SwatchImage>
<URL>http://ecx.images-amazon.com/images/I/615ixizvwKL._SL30_.jpg</URL>
<Height Units="pixels">30</Height>
<Width Units="pixels">30</Width>
 </SwatchImage>
 <SmallImage>
<URL>http://ecx.images-amazon.com/images/I/615ixizvwKL._SL75_.jpg</URL>
<Height Units="pixels">75</Height>
<Width Units="pixels">75</Width>
 </SmallImage>
 <ThumbnailImage>
<URL>http://ecx.images-amazon.com/images/I/615ixizvwKL._SL75_.jpg</URL>
<Height Units="pixels">75</Height>
<Width Units="pixels">75</Width>
 </ThumbnailImage>
 <TinyImage>
<URL>http://ecx.images-amazon.com/images/I/615ixizvwKL._SL110_.jpg</URL>
<Height Units="pixels">110</Height>
<Width Units="pixels">110</Width>
 </TinyImage>
 <MediumImage>
<URL>http://ecx.images-amazon.com/images/I/615ixizvwKL._SL160_.jpg</URL>
<Height Units="pixels">160</Height>
<Width Units="pixels">160</Width>
 </MediumImage>
 <LargeImage>
<URL>http://ecx.images-amazon.com/images/I/615ixizvwKL.jpg</URL>
<Height Units="pixels">500</Height>
<Width Units="pixels">500</Width>
 </LargeImage>
 </ImageSet>
 <ImageSet Category="variant">
 <SwatchImage>
<URL>http://ecx.images-amazon.com/images/I/61B3kk0YSTL._SL30_.jpg</URL>
<Height Units="pixels">30</Height>
<Width Units="pixels">30</Width>
 </SwatchImage>
 <SmallImage>
<URL>http://ecx.images-amazon.com/images/I/61B3kk0YSTL._SL75_.jpg</URL>
<Height Units="pixels">75</Height>
<Width Units="pixels">75</Width>
 </SmallImage>
 <ThumbnailImage>
<URL>http://ecx.images-amazon.com/images/I/61B3kk0YSTL._SL75_.jpg</URL>
<Height Units="pixels">75</Height>
<Width Units="pixels">75</Width>
 </ThumbnailImage>
 <TinyImage>
<URL>http://ecx.images-amazon.com/images/I/61B3kk0YSTL._SL110_.jpg</URL>
<Height Units="pixels">110</Height>
<Width Units="pixels">110</Width>
 </TinyImage>
 <MediumImage>
<URL>http://ecx.images-amazon.com/images/I/61B3kk0YSTL._SL160_.jpg</URL>
<Height Units="pixels">160</Height>
<Width Units="pixels">160</Width>
 </MediumImage>
 <LargeImage>
<URL>http://ecx.images-amazon.com/images/I/61B3kk0YSTL.jpg</URL>
<Height Units="pixels">500</Height>
<Width Units="pixels">500</Width>
 </LargeImage>
 </ImageSet>
 <ImageSet Category="primary">
 <SwatchImage>
<URL>http://ecx.images-amazon.com/images/I/616QzGUuq4L._SL30_.jpg</URL>
<Height Units="pixels">22</Height>
<Width Units="pixels">30</Width>
 </SwatchImage>
 <SmallImage>
<URL>http://ecx.images-amazon.com/images/I/616QzGUuq4L._SL75_.jpg</URL>
<Height Units="pixels">56</Height>
<Width Units="pixels">75</Width>
 </SmallImage>
 <ThumbnailImage>
<URL>http://ecx.images-amazon.com/images/I/616QzGUuq4L._SL75_.jpg</URL>
<Height Units="pixels">56</Height>
<Width Units="pixels">75</Width>
 </ThumbnailImage>
 <TinyImage>
<URL>http://ecx.images-amazon.com/images/I/616QzGUuq4L._SL110_.jpg</URL>
<Height Units="pixels">82</Height>
<Width Units="pixels">110</Width>
 </TinyImage>
 <MediumImage>
<URL>http://ecx.images-amazon.com/images/I/616QzGUuq4L._SL160_.jpg</URL>
<Height Units="pixels">120</Height>
<Width Units="pixels">160</Width>
 </MediumImage>
 <LargeImage>
<URL>http://ecx.images-amazon.com/images/I/616QzGUuq4L.jpg</URL>
<Height Units="pixels">375</Height>
<Width Units="pixels">500</Width>
 </LargeImage>
 </ImageSet>
 </ImageSets>
 <ItemAttributes>
<Manufacturer>FunAir</Manufacturer>
<ProductGroup>Toy</ProductGroup>
<Title>Gaga Ball Pit</Title>
 </ItemAttributes>
 <OfferSummary>
 <LowestNewPrice>
<Amount>299500</Amount>
<CurrencyCode>USD</CurrencyCode>
<FormattedPrice>$2,995.00</FormattedPrice>
 </LowestNewPrice>
<TotalNew>1</TotalNew>
<TotalUsed>0</TotalUsed>
<TotalCollectible>0</TotalCollectible>
<TotalRefurbished>0</TotalRefurbished>
 </OfferSummary>
 <Offers>
<TotalOffers>0</TotalOffers>
<TotalOfferPages>0</TotalOfferPages>
<MoreOffersUrl>0</MoreOffersUrl>
 </Offers>
 </Item>
 </Items>
 </ItemLookupResponse>